oso/__init__.py
oso_adil-0.1.0.dist-info/METADATA
oso_adil-0.1.0.dist-info/WHEEL
oso_adil/__init__.py
oso_adil-0.1.0.dist-info/RECORD
