Metadata-Version: 2.1
Name: oso-adil
Version: 0.1.0
License: MIT
Requires-Python: >=3.12
Requires-Dist: setuptools>=68.2.2
Requires-Dist: cffi~=1.15
Requires-Dist: dataclasses; python_version < "3.7"
